articulated_ssm_both_sides/FemurModel.py
articulated_ssm_both_sides/FitASM.py
articulated_ssm_both_sides/FitASM_2.py
articulated_ssm_both_sides/LandmarkHandler.py
articulated_ssm_both_sides/LowerLimb.py
articulated_ssm_both_sides/LowerLimbSide.py
articulated_ssm_both_sides/MainASM.py
articulated_ssm_both_sides/MainASM_LOO.py
articulated_ssm_both_sides/MainASM_train_test.py
articulated_ssm_both_sides/PLSR.py
articulated_ssm_both_sides/PatellaModel.py
articulated_ssm_both_sides/PelvisModel.py
articulated_ssm_both_sides/SSMHandler.py
articulated_ssm_both_sides/SaveMesh.py
articulated_ssm_both_sides/SegmentationHandler.py
articulated_ssm_both_sides/TibiaFibulaModel.py
articulated_ssm_both_sides/__init__.py
articulated_ssm_both_sides/correct_markers.py
articulated_ssm_both_sides/prediction_error_geometry.py
articulated_ssm_both_sides/coupled_ssm/pel_fem_tib_fib_both_side/Coupled_SSM_face_nrs_per_bone_mesh_left.txt
articulated_ssm_both_sides/coupled_ssm/pel_fem_tib_fib_both_side/Coupled_SSM_face_nrs_per_bone_mesh_right.txt
articulated_ssm_both_sides/coupled_ssm/pel_fem_tib_fib_both_side/Coupled_SSM_node_nrs_per_bone_mesh_left.txt
articulated_ssm_both_sides/coupled_ssm/pel_fem_tib_fib_both_side/Coupled_SSM_node_nrs_per_bone_mesh_right.txt
articulated_ssm_both_sides/coupled_ssm/pel_fem_tib_fib_both_side/shape_model_left_side.pc.npz
articulated_ssm_both_sides/coupled_ssm/pel_fem_tib_fib_both_side/shape_model_left_side_mean.ply
articulated_ssm_both_sides/coupled_ssm/pel_fem_tib_fib_both_side/shape_model_right_side.pc.npz
articulated_ssm_both_sides/coupled_ssm/pel_fem_tib_fib_both_side/shape_model_right_side_mean.ply
articulated_ssm_both_sides/coupled_ssm_regions_local/femur/femur_head_left_verts.txt
articulated_ssm_both_sides/coupled_ssm_regions_local/femur/femur_head_right_verts.txt
articulated_ssm_both_sides/coupled_ssm_regions_local/femur/knee_node_nrs_femur_left.txt
articulated_ssm_both_sides/coupled_ssm_regions_local/femur/knee_node_nrs_femur_right.txt
articulated_ssm-0.1.5.dist-info/METADATA
articulated_ssm-0.1.5.dist-info/WHEEL
articulated_ssm-0.1.5.dist-info/top_level.txt
articulated_ssm-0.1.5.dist-info/RECORD
