Metadata-Version: 2.4
Name: articulated-ssm
Version: 0.1.5
Summary: Python code for articulated statistical shape model generation.
Author-email: Laura Carman <laura.carman@auckland.ac.nz>, Timothy Salemink <tim.nicolas@outlook.com>
Project-URL: Repository, https://github.com/lauracarman/articulated-ssm_both_sides
Requires-Dist: numpy
Requires-Dist: scipy
Requires-Dist: pandas
Requires-Dist: scikit-learn==1.6.1
Requires-Dist: gias3.common
Requires-Dist: gias3.learning
Requires-Dist: gias3.mesh
Requires-Dist: gias3.musculoskeletal
Requires-Dist: gias3.registration
